{
    "movies": {
        "cast": [
            {
                "adult": false,
                "backdrop_path": "/zp5bc23EPflpLhkCObsFFOL3psw.jpg",
                "genre_ids": [
                    18,
                    35
                ],
                "id": 74534,
                "original_language": "en",
                "original_title": "The Best Exotic Marigold Hotel",
                "overview": "British retirees travel to India to take up residence in what they believe is a newly restored hotel. Less luxurious than its advertisements, the Marigold Hotel nevertheless slowly begins to charm in unexpected ways as the residents find new purpose in their old age.",
                "popularity": 2.3375,
                "poster_path": "/gNWiOKTWDvPTpr7QfPWk18gLftz.jpg",
                "release_date": "2012-02-23",
                "title": "The Best Exotic Marigold Hotel",
                "video": false,
                "vote_average": 6.956,
                "vote_count": 1395,
                "character": "Guarika",
                "credit_id": "5a4530059251411f5107f86f",
                "order": 23
            }
        ],
        "crew": []
    },
    "details": {
        "adult": false,
        "also_known_as": [
            "Neena Kuljarni",
            "Neena Kulkarni",
            "Nini Kulkarni",
            " \u0928\u0940\u0928\u093e \u0915\u0941\u0932\u0915\u0930\u094d\u0923\u0940"
        ],
        "biography": "",
        "birthday": null,
        "deathday": null,
        "gender": 1,
        "homepage": null,
        "id": 1238307,
        "imdb_id": "nm0474620",
        "known_for_department": "Acting",
        "name": "Nina Kulkarni",
        "place_of_birth": null,
        "popularity": 0.1157,
        "profile_path": "/m3UAaFNz2RjzEpdZVXEUUk6RdzQ.jpg"
    }
}