{
    "movies": {
        "cast": [
            {
                "adult": false,
                "backdrop_path": "/dmj6rictIMGfDbTv6pxeifyqs3I.jpg",
                "genre_ids": [
                    18,
                    10749
                ],
                "id": 97365,
                "original_language": "fr",
                "original_title": "De rouille et d'os",
                "overview": "Put in charge of his young son, Ali leaves Belgium for Antibes to live with his sister and her husband as a family. Ali's bond with Stephanie, a killer whale trainer, grows deeper after Stephanie suffers a horrible accident.",
                "popularity": 6.9542,
                "poster_path": "/6bcerd7CeQ5y5Dilym1O2C8c8Gl.jpg",
                "release_date": "2012-05-17",
                "title": "Rust and Bone",
                "video": false,
                "vote_average": 7.166,
                "vote_count": 1416,
                "character": "Stephanie's Mother",
                "credit_id": "52fe49dd9251416c750d5e3f",
                "order": 14
            }
        ],
        "crew": []
    },
    "details": {
        "adult": false,
        "also_known_as": [
            "    Fran\u00e7oise Michaux"
        ],
        "biography": "Fran\u00e7oise Michaud was born in Dijon, France. She graduated in humanities and cinema studies in Paris. After she began an acting career in France, she decided to go to Los Angeles (California) where she followed sessions of the Actors Studio. She also studied screenwriting at UCLA. At the same time she started to take photographs \u2013 making portraits of musicians, actors, directors, published in the press- as well as to take pictures on sets while shooting movies.",
        "birthday": "1963-01-01",
        "deathday": null,
        "gender": 1,
        "homepage": "https://francoise-michaud.fr/",
        "id": 144261,
        "imdb_id": "nm0584719",
        "known_for_department": "Acting",
        "name": "Fran\u00e7oise Michaud",
        "place_of_birth": "Dijon, C\u00f4te-d'Or, France",
        "popularity": 0.1079,
        "profile_path": "/40tTa9YmMg5YKhXdc69oZlAfxI3.jpg"
    }
}