{
    "movies": {
        "cast": [
            {
                "adult": false,
                "backdrop_path": "/3z8cveYwdIz2IZRhm6cHu8f2HRT.jpg",
                "genre_ids": [
                    35
                ],
                "id": 375794,
                "original_language": "es",
                "original_title": "No manches, Frida",
                "overview": "After being released from prison, Zequi, a bank robber, sets out to recover money buried by his accomplice; but is horrified to learn that a high school gymnasium is now over the site where the loot is hidden.",
                "popularity": 5.3856,
                "poster_path": "/6HfyXfIEywLa2HvcswKi44dDKxL.jpg",
                "release_date": "2016-09-02",
                "title": "No manches, Frida",
                "video": false,
                "vote_average": 7.7,
                "vote_count": 925,
                "character": "Cuquis",
                "credit_id": "57c4f364c3a36846fd002b9b",
                "order": 11
            }
        ],
        "crew": []
    },
    "details": {
        "adult": false,
        "also_known_as": [],
        "biography": "",
        "birthday": null,
        "deathday": null,
        "gender": 0,
        "homepage": null,
        "id": 1672141,
        "imdb_id": null,
        "known_for_department": "Acting",
        "name": "Pamela Moreno",
        "place_of_birth": null,
        "popularity": 0.0143,
        "profile_path": null
    }
}