{
    "movies": {
        "cast": [
            {
                "adult": false,
                "backdrop_path": "/sfoaAbgEQlQI8dBFJsiIdXiLI7x.jpg",
                "genre_ids": [
                    35,
                    18
                ],
                "id": 595975,
                "original_language": "fr",
                "original_title": "La Belle \u00c9poque",
                "overview": "Victor, a disillusioned 60-something whose marriage is on the rocks, opts to relive the week of his life when, 40 years earlier, he met his true love through a company that allows customers to return to the time period of their choosing.",
                "popularity": 1.8531,
                "poster_path": "/eHojoVxYRyqGABgoiTYyfkYqTra.jpg",
                "release_date": "2019-11-06",
                "title": "La Belle \u00c9poque",
                "video": false,
                "vote_average": 7.4,
                "vote_count": 1036,
                "character": "Am\u00e9lie",
                "credit_id": "5cc71f0c0e0a264ef4eef2f3",
                "order": 7
            },
            {
                "adult": false,
                "backdrop_path": "/flqONlzGNUkGCJr9BfBhGNLYo6B.jpg",
                "genre_ids": [
                    35,
                    36
                ],
                "id": 544510,
                "original_language": "fr",
                "original_title": "Edmond",
                "overview": "Paris, France, December 1897. The young playwright Edmond Rostand feels like a failure. Inspiration has abandoned him. Married and father of two children, desperate and penniless, he persuades the great actor Constant Coquelin to perform the main role in his new play. But there is a problem: Coquelin wants to premiere it at Christmas and Edmond has not written a single word.",
                "popularity": 1.7565,
                "poster_path": "/9Y1VxSfJdu8fqQqgX0x6OObxvUw.jpg",
                "release_date": "2018-11-10",
                "title": "Cyrano, My Love",
                "video": false,
                "vote_average": 7.5,
                "vote_count": 516,
                "character": "Jacqueline",
                "credit_id": "5dea5e4e4e67420015a47380",
                "order": 20
            }
        ],
        "crew": []
    },
    "details": {
        "adult": false,
        "also_known_as": [
            "Jeanne Arenes"
        ],
        "biography": "",
        "birthday": null,
        "deathday": null,
        "gender": 1,
        "homepage": null,
        "id": 1672709,
        "imdb_id": "nm5286974",
        "known_for_department": "Acting",
        "name": "Jeanne Ar\u00e8nes",
        "place_of_birth": null,
        "popularity": 0.1012,
        "profile_path": "/cCH24asznz5ExUqUZTlU3lMmQrI.jpg"
    }
}