{
    "movies": {
        "cast": [
            {
                "adult": false,
                "backdrop_path": "/mAxA5ltgqNXLXlm7PO5XrWSo9U1.jpg",
                "genre_ids": [
                    28,
                    35,
                    14,
                    12
                ],
                "id": 6978,
                "original_language": "en",
                "original_title": "Big Trouble in Little China",
                "overview": "Truck driver Jack Burton gets embroiled in a supernatural battle when his best friend Wang Chi's green-eyed fianc\u00e9e is kidnapped by henchmen of the sorcerer Lo Pan, who must marry a girl with green eyes in order to return to the human realm.",
                "popularity": 6.1013,
                "poster_path": "/aeGy6SZua7eFXEZP9zAvrLkkbI2.jpg",
                "release_date": "1986-05-30",
                "title": "Big Trouble in Little China",
                "video": false,
                "vote_average": 7.212,
                "vote_count": 3163,
                "character": "Wing Kong Hatchet Man",
                "credit_id": "57d4bb8a925141366700258e",
                "order": 37
            }
        ],
        "crew": []
    },
    "details": {
        "adult": false,
        "also_known_as": [],
        "biography": "Nathan Jung (November 29, 1946 \u2013 April 24, 2021) was an American actor and stuntman. Due to his height, he was usually cast in \"heavy\" or \"enforcer\" roles.",
        "birthday": "1946-11-29",
        "deathday": "2021-04-24",
        "gender": 2,
        "homepage": null,
        "id": 1677323,
        "imdb_id": "nm0432574",
        "known_for_department": "Acting",
        "name": "Nathan Jung",
        "place_of_birth": "Bakersfield, California, USA",
        "popularity": 0.0602,
        "profile_path": "/kPiRa6zraaYatfmO2ik2cz0KkAS.jpg"
    }
}