{
    "movies": {
        "cast": [
            {
                "adult": false,
                "backdrop_path": "/yFkUPqBuUnbhYbQL8VFpTrAT9za.jpg",
                "genre_ids": [
                    18,
                    878,
                    9648
                ],
                "id": 686,
                "original_language": "en",
                "original_title": "Contact",
                "overview": "A radio astronomer receives the first extraterrestrial radio signal ever picked up on Earth. As the world powers scramble to decipher the message and decide upon a course of action, she must make some difficult decisions between her beliefs, the truth, and reality.",
                "popularity": 8.2728,
                "poster_path": "/bCpMIywuNZeWt3i5UMLEIc0VSwM.jpg",
                "release_date": "1997-07-11",
                "title": "Contact",
                "video": false,
                "vote_average": 7.435,
                "vote_count": 4708,
                "character": "Protester (uncredited)",
                "credit_id": "5908d1a4c3a36858d600f7a3",
                "order": 123
            },
            {
                "adult": false,
                "backdrop_path": "/67HggiWaP9ZLv5sPYmyRV37yAJM.jpg",
                "genre_ids": [
                    35,
                    18,
                    10749
                ],
                "id": 13,
                "original_language": "en",
                "original_title": "Forrest Gump",
                "overview": "A man with a low IQ has accomplished great things in his life and been present during significant historic events\u2014in each case, far exceeding what anyone imagined he could do. But despite all he has achieved, his one true love eludes him.",
                "popularity": 18.309,
                "poster_path": "/arw2vcBveWOVZr6pxd9XTd1TdQa.jpg",
                "release_date": "1994-06-23",
                "title": "Forrest Gump",
                "video": false,
                "vote_average": 8.5,
                "vote_count": 28632,
                "character": "Student Protester (uncredited)",
                "credit_id": "6717867450a6eb0bfbc28278",
                "order": 127
            }
        ],
        "crew": []
    },
    "details": {
        "adult": false,
        "also_known_as": [
            "Eric Wendell"
        ],
        "biography": "",
        "birthday": "1973-06-12",
        "deathday": null,
        "gender": 2,
        "homepage": null,
        "id": 1720797,
        "imdb_id": "nm0920829",
        "known_for_department": "Acting",
        "name": "Eric Alan Wendell",
        "place_of_birth": "Wheeling, West Virginia, USA",
        "popularity": 0.0453,
        "profile_path": null
    }
}