{
    "movies": {
        "cast": [
            {
                "adult": false,
                "backdrop_path": "/eY6bnNP10bWljC19v8UXAScHyuP.jpg",
                "genre_ids": [
                    18,
                    80,
                    53
                ],
                "id": 1538,
                "original_language": "en",
                "original_title": "Collateral",
                "overview": "Cab driver Max picks up a man who offers him $600 to drive him around. But the promise of easy money sours when Max realizes his fare is an assassin.",
                "popularity": 5.265,
                "poster_path": "/nV5316WUsVij8sVXLCF1g7TFitg.jpg",
                "release_date": "2004-08-04",
                "title": "Collateral",
                "video": false,
                "vote_average": 7.234,
                "vote_count": 5930,
                "character": "Police Helicopter Co-Pilot",
                "credit_id": "5ee68d830cb3350022bfcf34",
                "order": 80
            }
        ],
        "crew": [
            {
                "adult": false,
                "backdrop_path": "/sctvs9cUwJD15qlTlrsh2BXsK75.jpg",
                "genre_ids": [
                    28,
                    80,
                    18
                ],
                "id": 111,
                "original_language": "en",
                "original_title": "Scarface",
                "overview": "After getting a green card in exchange for assassinating a Cuban government official, Tony Montana stakes a claim on the drug trade in Miami. Viciously murdering anyone who stands in his way, Tony eventually becomes the biggest drug lord in the state, controlling nearly all the cocaine that comes through Miami. But increased pressure from the police, wars with Colombian drug cartels and his own drug-fueled paranoia serve to fuel the flames of his eventual downfall.",
                "popularity": 12.0712,
                "poster_path": "/iQ5ztdjvteGeboxtmRdXEChJOHh.jpg",
                "release_date": "1983-12-09",
                "title": "Scarface",
                "video": false,
                "vote_average": 8.16,
                "vote_count": 12462,
                "credit_id": "65162c3c93bd6900c4de13ea",
                "department": "Crew",
                "job": "Stunts"
            },
            {
                "adult": false,
                "backdrop_path": "/j1xaeJZOEOiVBD1rk3dg4YaAk23.jpg",
                "genre_ids": [
                    28,
                    12,
                    18,
                    10751
                ],
                "id": 1885,
                "original_language": "en",
                "original_title": "The Karate Kid",
                "overview": "New Jersey teen Daniel LaRusso moves to Los Angeles with his mother, and soon strikes up a relationship with Ali. He quickly finds himself the target of bullying by a group of thugs, led by Ali's ex-boyfriend Johnny, who study karate at the Cobra Kai dojo under ruthless sensei John Kreese. Fortunately, Daniel befriends Mr. Miyagi, an unassuming repairman who just happens to be a martial arts master himself. Miyagi takes Daniel under his wing, training him in a more compassionate form of karate for self-defense and, later, preparing him to compete against the brutal Cobra Kai.",
                "popularity": 7.1065,
                "poster_path": "/1mp4ViklKvA0WXXsNvNx0RBuiit.jpg",
                "release_date": "1984-06-22",
                "title": "The Karate Kid",
                "video": false,
                "vote_average": 7.209,
                "vote_count": 4474,
                "credit_id": "65616839706e5600c4baacb3",
                "department": "Crew",
                "job": "Stunts"
            },
            {
                "adult": false,
                "backdrop_path": "/vfo2dzdXnoArYwrkM7kw1vgb7dL.jpg",
                "genre_ids": [
                    878,
                    28,
                    12,
                    53
                ],
                "id": 174,
                "original_language": "en",
                "original_title": "Star Trek VI: The Undiscovered Country",
                "overview": "After years of war, the Federation and the Klingon empire find themselves on the brink of a peace summit when a Klingon ship is nearly destroyed by an apparent attack from the Enterprise. Both worlds brace for what may be their deadliest encounter.",
                "popularity": 1.8635,
                "poster_path": "/tvTOJD7Gz668GLy2nNdLRQvpPsv.jpg",
                "release_date": "1991-12-06",
                "title": "Star Trek VI: The Undiscovered Country",
                "video": false,
                "vote_average": 7.03,
                "vote_count": 1333,
                "credit_id": "6438c37e87f3f2007649ecf4",
                "department": "Crew",
                "job": "Stunts"
            },
            {
                "adult": false,
                "backdrop_path": "/wN3dgwkiWSLrMVukPQIeccv5EJ6.jpg",
                "genre_ids": [
                    878,
                    12
                ],
                "id": 168,
                "original_language": "en",
                "original_title": "Star Trek IV: The Voyage Home",
                "overview": "When a huge alien probe enters the galaxy and begins to vaporize Earth's oceans, Kirk and his crew must travel back in time in order to bring back whales and save the planet.",
                "popularity": 5.3146,
                "poster_path": "/xY5TzGXJOB3L9rhZ1MbbPyVlW5J.jpg",
                "release_date": "1986-11-26",
                "title": "Star Trek IV: The Voyage Home",
                "video": false,
                "vote_average": 7.157,
                "vote_count": 1562,
                "credit_id": "6438c0b381a7fc0078731610",
                "department": "Crew",
                "job": "Stunts"
            },
            {
                "adult": false,
                "backdrop_path": "/yFPaqqXMGsdOKit3fsAJ9tqPJRP.jpg",
                "genre_ids": [
                    80,
                    18,
                    53
                ],
                "id": 242582,
                "original_language": "en",
                "original_title": "Nightcrawler",
                "overview": "When Lou Bloom, desperate for work, muscles into the world of L.A. crime journalism, he blurs the line between observer and participant to become the star of his own story. Aiding him in his effort is Nina, a TV-news veteran.",
                "popularity": 9.0762,
                "poster_path": "/j9HrX8f7GbZQm1BrBiR40uFQZSb.jpg",
                "release_date": "2014-10-23",
                "title": "Nightcrawler",
                "video": false,
                "vote_average": 7.705,
                "vote_count": 11237,
                "credit_id": "5f46fe042da84600333df4ea",
                "department": "Crew",
                "job": "Stunts"
            }
        ]
    },
    "details": {
        "adult": false,
        "also_known_as": [
            "Gary Len Silver"
        ],
        "biography": "",
        "birthday": null,
        "deathday": null,
        "gender": 2,
        "homepage": null,
        "id": 173207,
        "imdb_id": "nm0798795",
        "known_for_department": "Crew",
        "name": "Spike Silver",
        "place_of_birth": null,
        "popularity": 0.0784,
        "profile_path": null
    }
}