{
    "movies": {
        "cast": [
            {
                "adult": false,
                "backdrop_path": "/41ZWAGMttCr74dq7sAeh44QSJTQ.jpg",
                "genre_ids": [
                    28,
                    18,
                    36,
                    10752
                ],
                "id": 14433,
                "original_language": "en",
                "original_title": "Zulu",
                "overview": "In 1879, during the Anglo-Zulu War, man-of-the-people Lt. Chard and snooty Lt. Bromhead are in charge of defending the isolated and vastly outnumbered Natal outpost of Rorke's Drift from tribal hordes.",
                "popularity": 2.9397,
                "poster_path": "/9V7tl1kIb67ZPRRNlUdy3JvqEiA.jpg",
                "release_date": "1964-01-22",
                "title": "Zulu",
                "video": false,
                "vote_average": 7.389,
                "vote_count": 540,
                "character": "Cpl. Allen",
                "credit_id": "530f7818925141739000101c",
                "order": 8
            },
            {
                "adult": false,
                "backdrop_path": "/pRBCb6Hs6Xo4diXwpnBTcwMizE.jpg",
                "genre_ids": [
                    80,
                    53
                ],
                "id": 1485,
                "original_language": "en",
                "original_title": "Get Carter",
                "overview": "Jack Carter is a small-time hood working in London. When word reaches him of his brother's death, he travels to Newcastle to attend the funeral. Refusing to accept the police report of suicide, Carter seeks out his brother\u2019s friends and acquaintances to learn who murdered his sibling and why.",
                "popularity": 2.7835,
                "poster_path": "/3AytAYzJuPmS4Wo8X3jcsaN4oM3.jpg",
                "release_date": "1971-02-03",
                "title": "Get Carter",
                "video": false,
                "vote_average": 6.999,
                "vote_count": 525,
                "character": "Albert Swift",
                "credit_id": "5792aa8492514169c5001bc9",
                "order": 11
            }
        ],
        "crew": []
    },
    "details": {
        "adult": false,
        "also_known_as": [
            "Glyn Edwards",
            "John Glyn Edwards"
        ],
        "biography": "Glynn Edwards was a British television and film actor, probably best known for his role as the barman in the ITV comedy-drama Minder. His film credits included Zulu, The Ipcress File, Get Carter, Burke and Hare, Shaft in Africa, and Under Milk Wood. His first wife was the George and Mildred star Yootha Joyce.",
        "birthday": "1931-02-02",
        "deathday": "2018-05-23",
        "gender": 2,
        "homepage": null,
        "id": 175965,
        "imdb_id": "nm0250022",
        "known_for_department": "Acting",
        "name": "Glynn Edwards",
        "place_of_birth": "Penang, Malaysia",
        "popularity": 0.2252,
        "profile_path": "/pbx7qeF9axj8VBaNOZ6pofEmTjN.jpg"
    }
}