{
    "movies": {
        "cast": [
            {
                "adult": false,
                "backdrop_path": "/jpFcZH2eyh6gcoxCa637TrGe4bT.jpg",
                "genre_ids": [
                    28,
                    878
                ],
                "id": 2048,
                "original_language": "en",
                "original_title": "I, Robot",
                "overview": "In 2035, where robots are commonplace and abide by the three laws of robotics, a technophobic cop investigates an apparent suicide. Suspecting that a robot may be responsible for the death, his investigation leads him to believe that humanity may be in danger.",
                "popularity": 8.5531,
                "poster_path": "/efwv6F2lGaghjPpBRSINHtoEiZB.jpg",
                "release_date": "2004-07-15",
                "title": "I, Robot",
                "video": false,
                "vote_average": 6.956,
                "vote_count": 12214,
                "character": "Woman",
                "credit_id": "52fe4330c3a36847f804108b",
                "order": 16
            },
            {
                "adult": false,
                "backdrop_path": "/fGBJEfGjHmhg7nLAT0Jkcv9qV5e.jpg",
                "genre_ids": [
                    18,
                    35,
                    10749
                ],
                "id": 43347,
                "original_language": "en",
                "original_title": "Love & Other Drugs",
                "overview": "Maggie is an alluring free spirit who won't let anyone \u2013 or anything \u2013 tie her down. But she meets her match in Jamie, whose relentless and nearly infallible charm serves him well with the ladies and the cutthroat world of pharmaceutical sales. Maggie and Jamie's evolving relationship takes them both by surprise, as they find themselves under the influence of the ultimate drug: love.",
                "popularity": 9.7053,
                "poster_path": "/wZLM2uKJRYNchLmiCIjosX0rXy8.jpg",
                "release_date": "2010-11-04",
                "title": "Love & Other Drugs",
                "video": false,
                "vote_average": 7.043,
                "vote_count": 5367,
                "character": "La Boheme Receptionist",
                "credit_id": "5ab29ed4c3a3681cdc00af10",
                "order": 35
            }
        ],
        "crew": []
    },
    "details": {
        "adult": false,
        "also_known_as": [],
        "biography": "",
        "birthday": null,
        "deathday": null,
        "gender": 1,
        "homepage": null,
        "id": 176695,
        "imdb_id": "nm1285561",
        "known_for_department": "Acting",
        "name": "Sharon Wilkins",
        "place_of_birth": "Newburgh, New York, USA",
        "popularity": 1.2063,
        "profile_path": "/fVvxdXzgh9rKTZ7yeqSlwobG8v8.jpg"
    }
}