{
    "movies": {
        "cast": [
            {
                "adult": false,
                "backdrop_path": "/yvPbncYhMu9FfTjDhq0N5lgnVkO.jpg",
                "genre_ids": [
                    35,
                    10749,
                    18
                ],
                "id": 4951,
                "original_language": "en",
                "original_title": "10 Things I Hate About You",
                "overview": "On the first day at his new school, Cameron instantly falls for Bianca, the gorgeous girl of his dreams. The only problem is that Bianca is forbidden to date until her ill-tempered, completely un-dateable older sister Kat goes out, too. In an attempt to solve his problem, Cameron singles out the only guy who could possibly be a match for Kat: a mysterious bad boy with a nasty reputation of his own.",
                "popularity": 11.2158,
                "poster_path": "/ujERk3aKABXU3NDXOAxEQYTHe9A.jpg",
                "release_date": "1999-03-30",
                "title": "10 Things I Hate About You",
                "video": false,
                "vote_average": 7.595,
                "vote_count": 8523,
                "character": "Cameron James",
                "credit_id": "52fe43e6c3a36847f8077321",
                "order": 2
            },
            {
                "adult": false,
                "backdrop_path": "/A8qhyrvxSWreAN8yR5tLKhqIMYM.jpg",
                "genre_ids": [
                    18
                ],
                "id": 11171,
                "original_language": "en",
                "original_title": "Mysterious Skin",
                "overview": "A teenage hustler and a young man obsessed with alien abductions cross paths, together discovering a horrible, liberating truth.",
                "popularity": 5.9077,
                "poster_path": "/wgSwDqhl6Rt3cuSCwt5sNpPna3x.jpg",
                "release_date": "2005-03-30",
                "title": "Mysterious Skin",
                "video": false,
                "vote_average": 7.702,
                "vote_count": 1170,
                "character": "Neil McCormick",
                "credit_id": "52fe44079251416c750267bb",
                "order": 0
            },
            {
                "adult": false,
                "backdrop_path": "/30XLt1HzwOsdciWVaYVxlJq3cjH.jpg",
                "genre_ids": [
                    878,
                    12,
                    16,
                    10751,
                    14
                ],
                "id": 9016,
                "original_language": "en",
                "original_title": "Treasure Planet",
                "overview": "When space galleon cabin boy Jim Hawkins discovers a map to an intergalactic \"loot of a thousand worlds,\" a cyborg cook named John Silver teaches him to battle supernovas and space storms on their journey to find treasure.",
                "popularity": 8.0455,
                "poster_path": "/zMKatZ0c0NCoKzfizaCzVUcbKMf.jpg",
                "release_date": "2002-11-26",
                "title": "Treasure Planet",
                "video": false,
                "vote_average": 7.562,
                "vote_count": 4404,
                "character": "Jim Hawkins (voice)",
                "credit_id": "52fe44d1c3a36847f80abded",
                "order": 0
            },
            {
                "adult": false,
                "backdrop_path": "/gqby0RhyehP3uRrzmdyUZ0CgPPe.jpg",
                "genre_ids": [
                    28,
                    878,
                    12
                ],
                "id": 27205,
                "original_language": "en",
                "original_title": "Inception",
                "overview": "Cobb, a skilled thief who commits corporate espionage by infiltrating the subconscious of his targets is offered a chance to regain his old life as payment for a task considered to be impossible: \"inception\", the implantation of another person's idea into a target's subconscious.",
                "popularity": 27.091,
                "poster_path": "/ljsZTbVsrQSqZgWeep2B1QiDKuh.jpg",
                "release_date": "2010-07-15",
                "title": "Inception",
                "video": false,
                "vote_average": 8.37,
                "vote_count": 37957,
                "character": "Arthur",
                "credit_id": "52fe4534c3a368484e04de0b",
                "order": 1
            },
            {
                "adult": false,
                "backdrop_path": "/yq9g4RGM1mEMBoSL5HKVBy9MOPM.jpg",
                "genre_ids": [
                    35,
                    18
                ],
                "id": 40807,
                "original_language": "en",
                "original_title": "50/50",
                "overview": "Inspired by a true story, a comedy centered on a 27-year-old guy who learns of his cancer diagnosis and his subsequent struggle to beat the disease.",
                "popularity": 3.4684,
                "poster_path": "/8f9tM9JVB4ETBhxlQcXIjLckArl.jpg",
                "release_date": "2011-09-30",
                "title": "50/50",
                "video": false,
                "vote_average": 7.174,
                "vote_count": 3897,
                "character": "Adam Lerner",
                "credit_id": "52fe45a4c3a36847f80d263d",
                "order": 0
            },
            {
                "adult": false,
                "backdrop_path": "/y2DB71C4nyIdMrANijz8mzvQtk6.jpg",
                "genre_ids": [
                    28,
                    80,
                    18,
                    53
                ],
                "id": 49026,
                "original_language": "en",
                "original_title": "The Dark Knight Rises",
                "overview": "Following the death of District Attorney Harvey Dent, Batman assumes responsibility for Dent's crimes to protect the late attorney's reputation and is subsequently hunted by the Gotham City Police Department. Eight years later, Batman encounters the mysterious Selina Kyle and the villainous Bane, a new terrorist leader who overwhelms Gotham's finest. The Dark Knight resurfaces to protect a city that has branded him an enemy.",
                "popularity": 18.3339,
                "poster_path": "/hr0L2aueqlP2BYUblTTjmtn0hw4.jpg",
                "release_date": "2012-07-17",
                "title": "The Dark Knight Rises",
                "video": false,
                "vote_average": 7.787,
                "vote_count": 23537,
                "character": "Blake",
                "credit_id": "52fe4781c3a36847f8139879",
                "order": 3
            },
            {
                "adult": false,
                "backdrop_path": "/1M2i4Mxd03elGOTmEkIvqrHfmyS.jpg",
                "genre_ids": [
                    35,
                    18,
                    10749
                ],
                "id": 19913,
                "original_language": "en",
                "original_title": "(500) Days of Summer",
                "overview": "Tom, greeting-card writer and hopeless romantic, is caught completely off-guard when his girlfriend, Summer, suddenly dumps him. He reflects on their 500 days together to try to figure out where their love affair went sour, and in doing so, Tom rediscovers his true passions in life.",
                "popularity": 8.6356,
                "poster_path": "/qXAuQ9hF30sQRsXf40OfRVl0MJZ.jpg",
                "release_date": "2009-07-17",
                "title": "(500) Days of Summer",
                "video": false,
                "vote_average": 7.297,
                "vote_count": 10577,
                "character": "Tom",
                "credit_id": "52fe47f89251416c750aba5b",
                "order": 0
            },
            {
                "adult": false,
                "backdrop_path": "/4GPCnwvTbsDleH5QIOyDLMsK8a2.jpg",
                "genre_ids": [
                    28,
                    53,
                    878
                ],
                "id": 59967,
                "original_language": "en",
                "original_title": "Looper",
                "overview": "In the year 2044, time travel has not yet been invented but in 30 years it will have been. When the mob wants to get rid of someone, they will send their target into the past where a looper, a hired gun, like Joe is waiting to mop up. Joe is getting rich and life is good until the day the mob decides to close the loop, sending back Joe's future self for assassination.",
                "popularity": 5.2515,
                "poster_path": "/sNjL6SqErDBE8OUZlrDLkexfsCj.jpg",
                "release_date": "2012-09-26",
                "title": "Looper",
                "video": false,
                "vote_average": 6.896,
                "vote_count": 10486,
                "character": "Joe",
                "credit_id": "52fe49a5c3a36847f81a523f",
                "order": 0
            },
            {
                "adult": false,
                "backdrop_path": "/q2Ev0aXGXm5Hnm12TVtvdgNhMnv.jpg",
                "genre_ids": [
                    36,
                    18,
                    12
                ],
                "id": 285783,
                "original_language": "en",
                "original_title": "The Walk",
                "overview": "The story of French high-wire artist Philippe Petit's attempt to cross the Twin Towers of the World Trade Center in 1974.",
                "popularity": 3.5774,
                "poster_path": "/tiESRqurrZwAC0hpERogOsBhjeg.jpg",
                "release_date": "2015-09-30",
                "title": "The Walk",
                "video": false,
                "vote_average": 6.995,
                "vote_count": 3267,
                "character": "Philippe Petit",
                "credit_id": "53fcf5acc3a3684c8000001a",
                "order": 0
            },
            {
                "adult": false,
                "backdrop_path": "/6OqfTNZBprTqScvNpssXP1lUYqm.jpg",
                "genre_ids": [
                    18,
                    10751
                ],
                "id": 293,
                "original_language": "en",
                "original_title": "A River Runs Through It",
                "overview": "The Maclean brothers, Paul and Norman, live a relatively idyllic life in rural Montana, spending much of their time fly fishing. The sons of a minister, the boys eventually part company when Norman moves east to attend college, leaving his rebellious brother to find trouble back home. When Norman finally returns, the siblings resume their fishing outings, and assess where they've been and where they're going.",
                "popularity": 9.321,
                "poster_path": "/aVP45oS2cBL4WtZ1kB7r8uarruB.jpg",
                "release_date": "1992-10-09",
                "title": "A River Runs Through It",
                "video": false,
                "vote_average": 7.03,
                "vote_count": 1135,
                "character": "Young Norman",
                "credit_id": "54f2896dc3a3681b71000d4c",
                "order": 11
            },
            {
                "adult": false,
                "backdrop_path": "/dKqa850uvbNSCaQCV4Im1XlzEtQ.jpg",
                "genre_ids": [
                    35,
                    80,
                    9648
                ],
                "id": 661374,
                "original_language": "en",
                "original_title": "Glass Onion: A Knives Out Mystery",
                "overview": "World-famous detective Benoit Blanc heads to Greece to peel back the layers of a mystery surrounding a tech billionaire and his eclectic crew of friends.",
                "popularity": 8.8316,
                "poster_path": "/vDGr1YdrlfbU9wxTOdpf3zChmv9.jpg",
                "release_date": "2022-11-23",
                "title": "Glass Onion: A Knives Out Mystery",
                "video": false,
                "vote_average": 7.043,
                "vote_count": 6094,
                "character": "Hourly Dong (voice)",
                "credit_id": "63befdea55c1f4009ff26b81",
                "order": 19
            },
            {
                "adult": false,
                "backdrop_path": "/mYZYVrQ2ghU3m79q7byeLzNXo1M.jpg",
                "genre_ids": [
                    18,
                    36,
                    80,
                    53
                ],
                "id": 302401,
                "original_language": "en",
                "original_title": "Snowden",
                "overview": "CIA employee Edward Snowden leaks thousands of classified documents to the press.",
                "popularity": 2.8716,
                "poster_path": "/yfK7zxNL63VWfluFuoUaJj5PdNw.jpg",
                "release_date": "2016-09-15",
                "title": "Snowden",
                "video": false,
                "vote_average": 7.1,
                "vote_count": 4469,
                "character": "Edward Snowden",
                "credit_id": "57f5cb6b9251413601002ae4",
                "order": 0
            },
            {
                "adult": false,
                "backdrop_path": "/v8Nf6Y1qL1Q3PWTBezXNPPaXqza.jpg",
                "genre_ids": [
                    18,
                    36
                ],
                "id": 556984,
                "original_language": "en",
                "original_title": "The Trial of the Chicago 7",
                "overview": "What was supposed to be a peaceful protest turned into a violent clash with the police. What followed was one of the most notorious trials in history.",
                "popularity": 3.17,
                "poster_path": "/ahf5cVdooMAlDRiJOZQNuLqa1Is.jpg",
                "release_date": "2020-09-25",
                "title": "The Trial of the Chicago 7",
                "video": false,
                "vote_average": 7.677,
                "vote_count": 3174,
                "character": "Richard Schultz",
                "credit_id": "5c54e00d0e0a265e19d1d2a3",
                "order": 3
            },
            {
                "adult": false,
                "backdrop_path": "/4HWAQu28e2yaWrtupFPGFkdNU7V.jpg",
                "genre_ids": [
                    35,
                    80,
                    9648
                ],
                "id": 546554,
                "original_language": "en",
                "original_title": "Knives Out",
                "overview": "When renowned crime novelist Harlan Thrombey is found dead at his estate just after his 85th birthday, the inquisitive and debonair Detective Benoit Blanc is mysteriously enlisted to investigate. From Harlan's dysfunctional family to his devoted staff, Blanc sifts through a web of red herrings and self-serving lies to uncover the truth behind Harlan's untimely death.",
                "popularity": 10.7766,
                "poster_path": "/pThyQovXQrw2m0s9x82twj48Jq4.jpg",
                "release_date": "2019-11-27",
                "title": "Knives Out",
                "video": false,
                "vote_average": 7.843,
                "vote_count": 13115,
                "character": "Detective Hardrock (voice)",
                "credit_id": "5dd9d1a712aabc0016926fb1",
                "order": 23
            }
        ],
        "crew": [
            {
                "adult": false,
                "backdrop_path": "/4GPCnwvTbsDleH5QIOyDLMsK8a2.jpg",
                "genre_ids": [
                    28,
                    53,
                    878
                ],
                "id": 59967,
                "original_language": "en",
                "original_title": "Looper",
                "overview": "In the year 2044, time travel has not yet been invented but in 30 years it will have been. When the mob wants to get rid of someone, they will send their target into the past where a looper, a hired gun, like Joe is waiting to mop up. Joe is getting rich and life is good until the day the mob decides to close the loop, sending back Joe's future self for assassination.",
                "popularity": 5.2515,
                "poster_path": "/sNjL6SqErDBE8OUZlrDLkexfsCj.jpg",
                "release_date": "2012-09-26",
                "title": "Looper",
                "video": false,
                "vote_average": 6.896,
                "vote_count": 10486,
                "credit_id": "52fe49a5c3a36847f81a527d",
                "department": "Production",
                "job": "Executive Producer"
            },
            {
                "adult": false,
                "backdrop_path": "/n2eUT4zQA2yYcKOgAFidgOyiFoH.jpg",
                "genre_ids": [
                    18,
                    37
                ],
                "id": 68718,
                "original_language": "en",
                "original_title": "Django Unchained",
                "overview": "With the help of a German bounty hunter, a freed slave sets out to rescue his wife from a brutal Mississippi plantation owner.",
                "popularity": 12.4836,
                "poster_path": "/7oWY8VDWW7thTzWh3OKYRkWUlD5.jpg",
                "release_date": "2012-12-25",
                "title": "Django Unchained",
                "video": false,
                "vote_average": 8.184,
                "vote_count": 27058,
                "credit_id": "5703f64f9251415bb90001ce",
                "department": "Crew",
                "job": "Thanks"
            }
        ]
    },
    "details": {
        "adult": false,
        "also_known_as": [
            "\uc870\uc149 \uace0\ub4e0 \ub808\ube57",
            "Joseph Leonard Gordon-Levitt",
            "Joey Gordon-Levitt",
            "Joe Gordon-Levitt",
            "Joseph Leonard Levitt",
            "\u0414\u0436\u043e\u0437\u0435\u0444 \u0413\u043e\u0440\u0434\u043e\u043d-\u041b\u0435\u0432\u0456\u0442\u0442",
            "\u30b8\u30e7\u30bb\u30d5\u30fb\u30b4\u30fc\u30c9\u30f3\uff1d\u30ec\u30d3\u30c3\u30c8",
            "\u062c\u0648\u0632\u0641 \u06af\u0648\u0631\u062f\u0648\u0646-\u0644\u0648\u06cc\u062a",
            "\u30b8\u30e7\u30bb\u30d5\u30fb\u30b4\u30fc\u30c9\u30f3=\u30ec\u30f4\u30a3\u30c3\u30c8",
            "\u7956\u745f\u592b\u54e5\u9813\u5229\u57df",
            "\u55ac\u745f\u592b\u00b7\u9ad8\u767b\u674e\u7dad"
        ],
        "biography": "Joseph Leonard Gordon-Levitt is an American actor and filmmaker. He has received various accolades, including nominations for the Golden Globe Award for Best Actor \u2013 Motion Picture Musical or Comedy for his leading performances in 500 Days of Summer (2009) and 50/50 (2011). He is the founder of the online media platform HitRecord whose projects such as HitRecord on TV (2014\u201315) and Create Together (2020) won him two Primetime Emmy Awards in the category of Outstanding Interactive Program.\n\nBorn in Los Angeles to a Jewish family, Gordon-Levitt began his acting career as a child, appearing in the films A River Runs Through It (1992), Holy Matrimony (1994), and Angels in the Outfield (1994), which earned him a Young Artist Award and a Saturn Award nomination. He played the role of Tommy Solomon in the TV series 3rd Rock from the Sun (1996\u20132001) for which he received three nominations at the Screen Actors Guild Awards. He had a supporting role in 10 Things I Hate About You (1999) and voiced Jim Hawkins in the Disney animated Treasure Planet (2002) before taking a break from acting to study at Columbia University, but dropped out in 2004 to resume his acting career.\n\nSince returning to acting, Gordon-Levitt has starred in Manic (2001), Mysterious Skin (2004), Brick (2005), The Lookout (2007), The Brothers Bloom (2008), Miracle at St. Anna (2008), G.I. Joe: The Rise of Cobra (2009), Inception (2010), Hesher (2010), Premium Rush (2012), The Dark Knight Rises (2012), Looper (2012), and Lincoln (2012). He portrayed Philippe Petit in the Robert Zemeckis-directed film The Walk (2015) and whistleblower Edward Snowden in the Oliver Stone film Snowden (2016). In 2020, he starred in the legal drama The Trial of the Chicago 7, for which he won the Critics' Choice Movie Award for Best Acting Ensemble and the Screen Actors Guild Award for Outstanding Performance by a Cast in a Motion Picture.\n\nIn 2013, he wrote and directed Don Jon, a comedy-drama film that was released to critical acclaim, earning him an Independent Spirit Award nomination for Best First Screenplay. He previously directed and edited two short films, both of which were released in 2010: Morgan M. Morgansen's Date with Destiny and Morgan and Destiny's Eleventeenth Date: The Zeppelin Zoo. In 2021, he wrote, directed and starred in a comedy drama series Mr. Corman on Apple TV+.",
        "birthday": "1981-02-17",
        "deathday": null,
        "gender": 2,
        "homepage": null,
        "id": 24045,
        "imdb_id": "nm0330687",
        "known_for_department": "Acting",
        "name": "Joseph Gordon-Levitt",
        "place_of_birth": "Los Angeles, California, USA",
        "popularity": 1.9218,
        "profile_path": "/4U9G4YwTlIEbAymBaseltS38eH4.jpg"
    }
}