{
    "movies": {
        "cast": [
            {
                "adult": false,
                "backdrop_path": "/vDQwbN2ymkMQ8ldL3Sc275FGBw3.jpg",
                "genre_ids": [
                    10752,
                    36,
                    53
                ],
                "id": 530915,
                "original_language": "en",
                "original_title": "1917",
                "overview": "At the height of the First World War, two young British soldiers must cross enemy territory and deliver a message that will stop a deadly attack on hundreds of soldiers.",
                "popularity": 9.7606,
                "poster_path": "/iZf0KyrE25z1sage4SYFLCCrMi9.jpg",
                "release_date": "2019-12-25",
                "title": "1917",
                "video": false,
                "vote_average": 7.987,
                "vote_count": 12990,
                "character": "Sergeant Wright",
                "credit_id": "649e6eebc9dbf901281163d6",
                "order": 41
            },
            {
                "adult": false,
                "backdrop_path": "/dq18nCTTLpy9PmtzZI6Y2yAgdw5.jpg",
                "genre_ids": [
                    28,
                    12,
                    878
                ],
                "id": 497698,
                "original_language": "en",
                "original_title": "Black Widow",
                "overview": "Natasha Romanoff, also known as Black Widow, confronts the darker parts of her ledger when a dangerous conspiracy with ties to her past arises. Pursued by a force that will stop at nothing to bring her down, Natasha must deal with her history as a spy and the broken relationships left in her wake long before she became an Avenger.",
                "popularity": 10.3258,
                "poster_path": "/7JPpIjhD2V0sKyFvhB9khUMa30d.jpg",
                "release_date": "2021-07-07",
                "title": "Black Widow",
                "video": false,
                "vote_average": 7.192,
                "vote_count": 10763,
                "character": "Russian Spetnaz (uncredited)",
                "credit_id": "5f7e1e66b7abb5003767618d",
                "order": 68
            }
        ],
        "crew": []
    },
    "details": {
        "adult": false,
        "also_known_as": [],
        "biography": "Ian Wilson is known for Argylle (2024), 1917 (2019) and Nova (2021).",
        "birthday": null,
        "deathday": null,
        "gender": 2,
        "homepage": null,
        "id": 2807157,
        "imdb_id": null,
        "known_for_department": "Acting",
        "name": "Ian Wilson",
        "place_of_birth": null,
        "popularity": 0.0143,
        "profile_path": null
    }
}