{
    "movies": {
        "cast": [
            {
                "adult": false,
                "backdrop_path": "/4tdV5AeojEdbvn6VpeQrbuDlmzs.jpg",
                "genre_ids": [
                    16,
                    18,
                    12,
                    14
                ],
                "id": 916224,
                "original_language": "ja",
                "original_title": "\u3059\u305a\u3081\u306e\u6238\u7de0\u307e\u308a",
                "overview": "Suzume, 17, lost her mother as a little girl. On her way to school, she meets a mysterious young man. But her curiosity unleashes a calamity that endangers the entire population of Japan, and so Suzume embarks on a journey to set things right.",
                "popularity": 8.5962,
                "poster_path": "/yStW1TXF5s7Tbtu9KjIZEaWl6HL.jpg",
                "release_date": "2022-11-11",
                "title": "Suzume",
                "video": false,
                "vote_average": 7.9,
                "vote_count": 1539,
                "character": "(voice)",
                "credit_id": "64a5f2fb724de100fff740ba",
                "order": 16
            }
        ],
        "crew": []
    },
    "details": {
        "adult": false,
        "also_known_as": [
            "\u4eca\u6d25\u5fc3\u4e4b\u4ecb"
        ],
        "biography": "",
        "birthday": null,
        "deathday": null,
        "gender": 2,
        "homepage": "https://profile.himawari.net/view/5921",
        "id": 4148883,
        "imdb_id": null,
        "known_for_department": "Acting",
        "name": "Shinnosuke Imazu",
        "place_of_birth": "Osaka, Japan",
        "popularity": 0.0143,
        "profile_path": null
    }
}