{
    "movies": {
        "cast": [
            {
                "adult": false,
                "backdrop_path": "/yfTZ2MSRWc06cBrFOsAF4Lebi4.jpg",
                "genre_ids": [
                    16,
                    35,
                    10751
                ],
                "id": 62214,
                "original_language": "en",
                "original_title": "Frankenweenie",
                "overview": "When a car hits young Victor's pet dog Sparky, Victor decides to bring him back to life the only way he knows how. But when the bolt-necked \"monster\" wreaks havoc and terror in the hearts of Victor's neighbors, he has to convince them that Sparky's still the good, loyal friend he was.",
                "popularity": 6.5353,
                "poster_path": "/yGjVbLVdZRBlZTTQVBsj2KUjL1s.jpg",
                "release_date": "2012-10-04",
                "title": "Frankenweenie",
                "video": false,
                "vote_average": 7.002,
                "vote_count": 3465,
                "character": "Edgar 'E' Gore (voice)",
                "credit_id": "52fe4676c3a368484e091f63",
                "order": 4
            }
        ],
        "crew": []
    },
    "details": {
        "adult": false,
        "also_known_as": [
            "\uc544\ud2f0\ucee4\uc2a4 \uc0e4\ud37c",
            "\u0622\u062a\u06cc\u06a9\u0627\u0633 \u0634\u0641\u0631"
        ],
        "biography": "From Wikipedia, the free encyclopedia.  Atticus Shaffer (born June 19, 1998) is an American actor, known for portraying Matty Newton in the 2009 supernatural horror-thriller film The Unborn and Brick Heck in the ABC comedy TV series, The Middle.  Description above from the Wikipedia article Atticus Shaffer, licensed under CC-BY-SA,full list of contributors on Wikipedia.",
        "birthday": "1998-06-19",
        "deathday": null,
        "gender": 2,
        "homepage": null,
        "id": 66646,
        "imdb_id": "nm2557831",
        "known_for_department": "Acting",
        "name": "Atticus Shaffer",
        "place_of_birth": "Santa Clarita, California, USA",
        "popularity": 0.6586,
        "profile_path": "/uZUZizKPSIiEiqVXh5IwIQBH2VX.jpg"
    }
}