{
    "movies": {
        "cast": [
            {
                "adult": false,
                "backdrop_path": "/4rHZyoFxGxvkMNiLFEqwm19HCtc.jpg",
                "genre_ids": [
                    18,
                    10749
                ],
                "id": 34653,
                "original_language": "en",
                "original_title": "A Single Man",
                "overview": "Set in Los Angeles in 1962, at the height of the Cuban missile crisis, is the story of a British college professor who dwells on the past and cannot see his future. We follow him through a single day, where a series of events and encounters ultimately lead him to decide if there is a meaning to life after the death of his long time partner, Jim.",
                "popularity": 3.36,
                "poster_path": "/AvqTb66bS1i1NjlPC76zvxo0taT.jpg",
                "release_date": "2009-12-11",
                "title": "A Single Man",
                "video": false,
                "vote_average": 7.3,
                "vote_count": 1598,
                "character": "Young Woman",
                "credit_id": "52fe45729251416c910329fd",
                "order": 19
            }
        ],
        "crew": []
    },
    "details": {
        "adult": false,
        "also_known_as": [
            "Elizabeth Harnois",
            "\u0627\u0644\u06cc\u0632\u0627\u0628\u062a \u0647\u0627\u0631\u0646\u0648\u06cc\u0633"
        ],
        "biography": "Elisabeth Harnois (born May 26, 1979) is an American television and film actress.",
        "birthday": "1979-05-26",
        "deathday": null,
        "gender": 1,
        "homepage": null,
        "id": 78197,
        "imdb_id": "nm0363699",
        "known_for_department": "Acting",
        "name": "Elisabeth Harnois",
        "place_of_birth": "Detroit, Michigan, USA",
        "popularity": 0.7104,
        "profile_path": "/yq9H8T5urAGhzvEBxbw4gBjvDN2.jpg"
    }
}